executioner/__init__.py
executioner/__main__.py
executioner/errors.py
executioner/evaluate.py
executioner/logging.py
executioner/program.py
executioner/settings.py
executioner/settings.yaml
executioner/utils.py
executioner/metric/__init__.py
executioner/metric/test/__init__.py
executioner/metric/test/test_basic.py
executioner/sandbox/__init__.py
executioner/sandbox/base_sandbox.py
executioner/sandbox/firejail.py
executioner/sandbox/no_sandbox.py
executioner/sandbox/test/__init__.py
executioner/sandbox/test/decorators.py
executioner/sandbox/test/language_tester.py
executioner/sandbox/test/sandbox_tester.py
executioner/sandbox/test/test_sandbox.py
executioner/test/__init__.py
executioner/test/test_errors.py
executioner/test/test_evaluate.py
executioner/test/test_program.py
executioner/test/test_settings.py
executioner/test/test_utils.py
pyExecutioner-0.0.15.dist-info/LICENSE
pyExecutioner-0.0.15.dist-info/METADATA
pyExecutioner-0.0.15.dist-info/WHEEL
pyExecutioner-0.0.15.dist-info/top_level.txt
pyExecutioner-0.0.15.dist-info/RECORD
