Metadata-Version: 2.1
Name: pyExecutioner
Version: 0.0.15
Summary: A library to execute code
Home-page: https://github.com/iCodeDevs/EXecutioner
Author: dravog
Author-email: dravog78@gmail.com
License: UNKNOWN
Project-URL: Bug Tracker, https://github.com/iCodeDevs/EXecutioner/issues
Platform: UNKNOWN
Classifier: Programming Language :: Python :: 3
Classifier: License :: OSI Approved :: GNU General Public License v3 (GPLv3)
Classifier: Operating System :: POSIX :: Linux
Classifier: Topic :: Software Development :: Libraries
Classifier: Development Status :: 3 - Alpha
Requires-Python: >=3.6
License-File: LICENSE
Requires-Dist: setuptools (>=42)
Requires-Dist: wheel
Requires-Dist: deepmerge (>=0.1.0)
Requires-Dist: PyYAML (>=5.4.1)
Requires-Dist: tabulate
